{"contribs_list": [{"rel_abundance": 0.21, "human_readable": "GAATCCCGCTTCTGTGTCTCCAGTC|nGACCGTGTGTGAGAAGATCATGGAGTTGCTGGGACAGAACGAGGTGGAA", "indel": {"total": 1, "details": [{"label": "g1", "value": 1}]}, "wt": false}, {"rel_abundance": 0.13, "human_readable": "GAATCCCGCTTCTGTGTCTCCAGTC|--CCGTGTGTGAGAAGATCATGGAGTTGCTGGGACAGAACGAGGTGGAAC", "indel": {"total": -2, "details": [{"label": "g1", "value": -2}]}, "wt": false}, {"rel_abundance": 0.11, "human_readable": "GAATCCCGCTTCTGTGTCTCCAGTC|----GTGTGTGAGAAGATCATGGAGTTGCTGGGACAGAACGAGGTGGAAC", "indel": {"total": -4, "details": [{"label": "g1", "value": -4}]}, "wt": false}, {"rel_abundance": 0.1, "human_readable": "GAATCCCGCTTCTGTGTCTCCAGTC|GACCGTGTGTGAGAAGATCATGGAGTTGCTGGGACAGAACGAGGTGGAAC", "indel": {"total": 0, "details": []}, "wt": true}, {"rel_abundance": 0.06, "human_readable": "GAATCCCGCTTCTGTGTCTCCAGTC|--------GTGAGAAGATCATGGAGTTGCTGGGACAGAACGAGGTGGAAC", "indel": {"total": -8, "details": [{"label": "g1", "value": -8}]}, "wt": false}, {"rel_abundance": 0.06, "human_readable": "GAATCCCGCTTCTGTGTCTCCAGTC|---------------GATCATGGAGTTGCTGGGACAGAACGAGGTGGAAC", "indel": {"total": -15, "details": [{"label": "g1", "value": -15}]}, "wt": false}, {"rel_abundance": 0.05, "human_readable": "GAATCCCGCTTCTGTGTCTCCAGTC|-------------------ATGGAGTTGCTGGGACAGAACGAGGTGGAAC", "indel": {"total": -19, "details": [{"label": "g1", "value": -19}]}, "wt": false}, {"rel_abundance": 0.04, "human_readable": "GAATCCCGCTTCTGTGTCTCCAGTC|----------------ATCATGGAGTTGCTGGGACAGAACGAGGTGGAAC", "indel": {"total": -16, "details": [{"label": "g1", "value": -16}]}, "wt": false}, {"rel_abundance": 0.03, "human_readable": "GAATCCCGCTTCTGTGTCTCCAGTC|-------TGTGAGAAGATCATGGAGTTGCTGGGACAGAACGAGGTGGAAC", "indel": {"total": -7, "details": [{"label": "g1", "value": -7}]}, "wt": false}, {"rel_abundance": 0.02, "human_readable": "GAATCCCGCTTCTGTGTCTCCAGTC|------------GAAGATCATGGAGTTGCTGGGACAGAACGAGGTGGAAC", "indel": {"total": -12, "details": [{"label": "g1", "value": -12}]}, "wt": false}, {"rel_abundance": 0.02, "human_readable": "GAATCCCGCTTCTGTGTCTCCAG--|--------------------TGGAGTTGCTGGGACAGAACGAGGTGGAAC", "indel": {"total": -22, "details": [{"label": "g1", "value": -22}]}, "wt": false}, {"rel_abundance": 0.02, "human_readable": "GAATCCCGCTTCTGTGTCTCCAGTC|nnnnGACCGTGTGTGAGAAGATCATGGAGTTGCTGGGACAGAACGAGGTG", "indel": {"total": 4, "details": [{"label": "g1", "value": 4}]}, "wt": false}, {"rel_abundance": 0.01, "human_readable": "GAATCCCGCTTCTGTGTCTCCAGTC|-----------AGAAGATCATGGAGTTGCTGGGACAGAACGAGGTGGAAC", "indel": {"total": -11, "details": [{"label": "g1", "value": -11}]}, "wt": false}, {"rel_abundance": 0.01, "human_readable": "GAATCCCGCTTCTGTGTCTCCAGTC|nnGACCGTGTGTGAGAAGATCATGGAGTTGCTGGGACAGAACGAGGTGGA", "indel": {"total": 2, "details": [{"label": "g1", "value": 2}]}, "wt": false}, {"rel_abundance": 0.01, "human_readable": "GAATCCCGCTTCTGTGTCTCCAGTC|nnnnnnnnnnnnnnnnGACCGTGTGTGAGAAGATCATGGAGTTGCTGGGA", "indel": {"total": 16, "details": [{"label": "g1", "value": 16}]}, "wt": false}, {"rel_abundance": 0.01, "human_readable": "GAATCCCGCTTCTGTGTCTCCAGTC|nnnnnnnnnnnnnnnnnnnGACCGTGTGTGAGAAGATCATGGAGTTGCTG", "indel": {"total": 19, "details": [{"label": "g1", "value": 19}]}, "wt": false}], "editing_outcomes": {"1": 21.0, "-2": 13.0, "-4": 11.0, "0": 10.0, "-8": 6.0, "-15": 6.0, "-19": 5.0, "-16": 4.0, "-7": 3.0, "-12": 2.0, "-22": 2.0, "4": 2.0, "-11": 1.0, "2": 1.0, "16": 1.0, "19": 1.0, "-1": 0.0, "-3": 0.0, "-5": 0.0, "-6": 0.0, "-9": 0.0, "-10": 0.0, "-13": 0.0, "-14": 0.0, "-17": 0.0, "-18": 0.0, "-20": 0.0, "-21": 0.0, "-23": 0.0, "-24": 0.0, "-25": 0.0, "-26": 0.0, "-27": 0.0, "-28": 0.0, "-29": 0.0, "-30": 0.0, "-31": 0.0, "-32": 0.0, "-33": 0.0, "-34": 0.0, "-35": 0.0, "-36": 0.0, "-37": 0.0, "-38": 0.0, "-39": 0.0, "-40": 0.0, "3": 0.0, "5": 0.0, "6": 0.0, "7": 0.0, "8": 0.0, "9": 0.0, "10": 0.0, "11": 0.0, "12": 0.0, "13": 0.0, "14": 0.0, "15": 0.0, "17": 0.0, "18": 0.0, "20": 0.0}, "multiplex": false}